CellPatchExtraction/__init__.py
CellPatchExtraction/.cellpose_model/CP_BM
CellPatchExtraction/.cellpose_model/CP_TU
CellPatchExtraction/.cellpose_model/CP_TU_MORE
CellPatchExtraction/.cellpose_model/__init__.py
CellPatchExtraction/src/__init__.py
CellPatchExtraction/src/extraction.py
CellPatchExtraction/src/utils.py
CellPatchExtraction-1.24.dist-info/METADATA
CellPatchExtraction-1.24.dist-info/WHEEL
CellPatchExtraction-1.24.dist-info/top_level.txt
CellPatchExtraction-1.24.dist-info/RECORD
