Metadata-Version: 2.1
Name: CellPatchExtraction
Version: 1.24
Home-page: https://github.com/SimonBon/CellPatchExtraction
Author: Simon Gutwein
Author-email: simon.gutwein@ccri.at
License: MIT
Classifier: License :: OSI Approved :: MIT License
Classifier: Programming Language :: Python
Classifier: Programming Language :: Python :: 3
Classifier: Programming Language :: Python :: 3.9
Requires-Dist: typing-extensions
Requires-Dist: scipy
Requires-Dist: numpy
Requires-Dist: tifffile
Requires-Dist: torch==2.0.1
Requires-Dist: cellpose==2.2.3
Requires-Dist: matplotlib
Requires-Dist: psutil
Requires-Dist: cellplot
